pyctor/__init__.py
pyctor/actor.py
pyctor-0.0.2.dist-info/LICENSE
pyctor-0.0.2.dist-info/METADATA
pyctor-0.0.2.dist-info/WHEEL
pyctor-0.0.2.dist-info/top_level.txt
pyctor-0.0.2.dist-info/RECORD
