Metadata-Version: 2.1
Name: pyctor
Version: 0.0.2
Summary: Minimalistic implementation of the actor concurrency model powered by asyncio.
Home-page: https://github.com/kweimann/pyctor
Author: Kuba Weimann
Author-email: kuba.weimann@gmail.com
License: MIT
Platform: UNKNOWN
Requires-Python: >=3.7.3
